Metadata-Version: 2.4
Name: sbyb
Version: 0.1.1
Summary: A comprehensive ML library that unifies the entire ML pipeline
Home-page: https://github.com/sbyb/sbyb
Author: Salimbinyousuf
Author-email: info@sbyb.ai
Project-URL: Bug Tracker, https://github.com/sbyb/sbyb/issues
Project-URL: Documentation, https://sbyb.readthedocs.io/
Project-URL: Source Code, https://github.com/sbyb/sbyb
Classifier: Programming Language :: Python :: 3
Classifier: Programming Language :: Python :: 3.8
Classifier: Programming Language :: Python :: 3.9
Classifier: Programming Language :: Python :: 3.10
Classifier: License :: OSI Approved :: MIT License
Classifier: Operating System :: OS Independent
Classifier: Development Status :: 4 - Beta
Classifier: Intended Audience :: Developers
Classifier: Intended Audience :: Science/Research
Classifier: Topic :: Scientific/Engineering :: Artificial Intelligence
Requires-Python: >=3.8
Requires-Dist: numpy>=1.20.0
Requires-Dist: pandas>=1.3.0
Requires-Dist: scikit-learn>=1.0.0
Requires-Dist: matplotlib>=3.4.0
Requires-Dist: seaborn>=0.11.0
Requires-Dist: plotly>=5.0.0
Requires-Dist: streamlit>=1.10.0
Requires-Dist: dash>=2.0.0
Requires-Dist: flask>=2.0.0
Requires-Dist: fastapi>=0.70.0
Requires-Dist: uvicorn>=0.15.0
Requires-Dist: shap>=0.40.0
Requires-Dist: lime>=0.2.0
Requires-Dist: eli5>=0.11.0
Requires-Dist: onnx>=1.10.0
Requires-Dist: onnxruntime>=1.8.0
Requires-Dist: tensorflow>=2.8.0
Requires-Dist: torch>=1.10.0
Requires-Dist: xgboost>=1.5.0
Requires-Dist: lightgbm>=3.3.0
Requires-Dist: catboost>=1.0.0
Requires-Dist: optuna>=2.10.0
Requires-Dist: hyperopt>=0.2.5
Requires-Dist: pyyaml>=6.0
Requires-Dist: tqdm>=4.62.0
Requires-Dist: joblib>=1.1.0
Requires-Dist: pytest>=6.2.5
Provides-Extra: dev
Requires-Dist: black; extra == "dev"
Requires-Dist: flake8; extra == "dev"
Requires-Dist: isort; extra == "dev"
Requires-Dist: mypy; extra == "dev"
Requires-Dist: pytest; extra == "dev"
Requires-Dist: pytest-cov; extra == "dev"
Requires-Dist: sphinx; extra == "dev"
Requires-Dist: sphinx-rtd-theme; extra == "dev"
Requires-Dist: twine; extra == "dev"
Requires-Dist: wheel; extra == "dev"
Provides-Extra: docs
Requires-Dist: sphinx; extra == "docs"
Requires-Dist: sphinx-rtd-theme; extra == "docs"
Requires-Dist: myst-parser; extra == "docs"
Provides-Extra: test
Requires-Dist: pytest; extra == "test"
Requires-Dist: pytest-cov; extra == "test"
Dynamic: author
Dynamic: author-email
Dynamic: classifier
Dynamic: description
Dynamic: description-content-type
Dynamic: home-page
Dynamic: project-url
Dynamic: provides-extra
Dynamic: requires-dist
Dynamic: requires-python
Dynamic: summary
